poweretl/utils/__init__.py
poweretl/utils/file/FileCommandSplitter.py
poweretl/utils/file/FileMerger.py
poweretl/utils/file/MultiFileReader.py
poweretl/utils/file/__init__.py
poweretl/utils/tests/ConfigReader.py
poweretl/utils/tests/TestConfig.py
poweretl/utils/tests/__init__.py
poweretl/utils/text/TokensReplacer.py
poweretl/utils/text/__init__.py
poweretl_utils-0.0.3a1.dist-info/METADATA
poweretl_utils-0.0.3a1.dist-info/WHEEL
poweretl_utils-0.0.3a1.dist-info/RECORD
